PyramidCookbookZhongwenban/README.md
PyramidCookbookZhongwenban/__init__.py
PyramidCookbookZhongwenban/__main__.py
PyramidCookbookZhongwenban/file.epub
PyramidCookbookZhongwenban/index.html
PyramidCookbookZhongwenban/css/__init__.py
PyramidCookbookZhongwenban/css/annotations.css
PyramidCookbookZhongwenban/css/main.css
PyramidCookbookZhongwenban/css/normalize.css
PyramidCookbookZhongwenban/css/popup.css
PyramidCookbookZhongwenban/font/__init__.py
PyramidCookbookZhongwenban/font/fontello.eot
PyramidCookbookZhongwenban/font/fontello.svg
PyramidCookbookZhongwenban/font/fontello.ttf
PyramidCookbookZhongwenban/font/fontello.woff
PyramidCookbookZhongwenban/img/__init__.py
PyramidCookbookZhongwenban/img/annotator-glyph-sprite.png
PyramidCookbookZhongwenban/img/annotator-icon-sprite.png
PyramidCookbookZhongwenban/img/apple-touch-icon.png
PyramidCookbookZhongwenban/img/cancelfullscreen.png
PyramidCookbookZhongwenban/img/close.png
PyramidCookbookZhongwenban/img/fullscreen.png
PyramidCookbookZhongwenban/img/loader.gif
PyramidCookbookZhongwenban/img/menu-icon.png
PyramidCookbookZhongwenban/img/save.png
PyramidCookbookZhongwenban/img/saved.png
PyramidCookbookZhongwenban/img/settings-s.png
PyramidCookbookZhongwenban/img/settings.png
PyramidCookbookZhongwenban/img/star.png
PyramidCookbookZhongwenban/js/__init__.py
PyramidCookbookZhongwenban/js/epub.js
PyramidCookbookZhongwenban/js/epub.min.js
PyramidCookbookZhongwenban/js/epub.min.map
PyramidCookbookZhongwenban/js/hooks.min.js
PyramidCookbookZhongwenban/js/hooks.min.map
PyramidCookbookZhongwenban/js/reader.js
PyramidCookbookZhongwenban/js/reader.js.map
PyramidCookbookZhongwenban/js/reader.min.js
PyramidCookbookZhongwenban/js/reader.min.map
PyramidCookbookZhongwenban/js/hooks/__init__.py
PyramidCookbookZhongwenban/js/hooks/extensions/__init__.py
PyramidCookbookZhongwenban/js/hooks/extensions/highlight.js
PyramidCookbookZhongwenban/js/libs/__init__.py
PyramidCookbookZhongwenban/js/libs/jquery.min.js
pyramid_cookbook_zhongwenban-2024.3.4.0.dist-info/METADATA
pyramid_cookbook_zhongwenban-2024.3.4.0.dist-info/WHEEL
pyramid_cookbook_zhongwenban-2024.3.4.0.dist-info/entry_points.txt
pyramid_cookbook_zhongwenban-2024.3.4.0.dist-info/top_level.txt
pyramid_cookbook_zhongwenban-2024.3.4.0.dist-info/RECORD
